airflow_sqlcmd_operator/__init__.py
airflow_sqlcmd_operator/sqlcmd.py
airflow_sqlcmd_operator-0.5.1.dist-info/LICENSE
airflow_sqlcmd_operator-0.5.1.dist-info/METADATA
airflow_sqlcmd_operator-0.5.1.dist-info/WHEEL
airflow_sqlcmd_operator-0.5.1.dist-info/top_level.txt
airflow_sqlcmd_operator-0.5.1.dist-info/RECORD
