Metadata-Version: 2.1
Name: airflow-sqlcmd-operator
Version: 0.5.1
Summary: Custom Airflow BashOperator for Microsoft sqlcmd
Home-page: https://github.com/dewes/airflow-sqlcmd-operator
Author: Rodrigo Dewes
Author-email: rdewes@gmail.com
License: MIT
Download-URL: https://github.com/dewes/airflow-sqlcmd-operator/archive/refs/tags/v_03.tar.gz
Keywords: Airflow,operator,SQLServer,sqlcmd
Platform: UNKNOWN
Classifier: Development Status :: 3 - Alpha
Classifier: Intended Audience :: Developers
Classifier: Topic :: Software Development :: Build Tools
Classifier: License :: OSI Approved :: MIT License
Classifier: Programming Language :: Python :: 3
Classifier: Programming Language :: Python :: 3.8
Requires-Dist: pathlib
Requires-Dist: apache-airflow (>=2.1)
